get_container_ip/__init__.py
get_container_ip/__main__.py
get_container_ip/cli.py
get_container_ip/get_ip.py
get_container_ip-0.1.0.dist-info/LICENSE
get_container_ip-0.1.0.dist-info/METADATA
get_container_ip-0.1.0.dist-info/WHEEL
get_container_ip-0.1.0.dist-info/top_level.txt
get_container_ip-0.1.0.dist-info/RECORD
