Metadata-Version: 2.2
Name: get_container_ip
Version: 0.1.0
Summary: Un package per ottenere l'indirizzo IP di un container.
Home-page: https://github.com/Koent-it/get_container_ip
Author: Koent S.r.l.
Author-email: tools@koent.it
Classifier: Programming Language :: Python :: 3
Classifier: License :: OSI Approved :: MIT License
Classifier: Operating System :: OS Independent
Requires-Python: >=3.6
License-File: LICENSE
Requires-Dist: argparse
Requires-Dist: logging
Dynamic: author
Dynamic: author-email
Dynamic: classifier
Dynamic: description
Dynamic: description-content-type
Dynamic: home-page
Dynamic: requires-dist
Dynamic: requires-python
Dynamic: summary
